dftopo/__init__.py
dftopo/dfps.py
justogres/Mongo.py
justogres/__init__.py
justogres/db.py
justogres/spreadsheets.py
justogres/utils.py
justogres-3.0.11.dist-info/LICENSE
justogres-3.0.11.dist-info/METADATA
justogres-3.0.11.dist-info/WHEEL
justogres-3.0.11.dist-info/top_level.txt
justogres-3.0.11.dist-info/RECORD
