Metadata-Version: 2.1
Name: justogres
Version: 3.0.11
Summary: This library is used to read or write data in Postgres, MongoDB (Only read) or Google Sheets
Home-page: https://github.com/justo-bi/justogres
Author: Jose Izam, Daniel Taiba
Author-email: jose.izam99@gmail.com, danielt.dtr@gmail.com
Project-URL: Bug Tracker, https://github.com/justo-bi/justogres
Classifier: Programming Language :: Python :: 3
Classifier: License :: OSI Approved :: MIT License
Classifier: Operating System :: OS Independent
Requires-Python: >=3.6
License-File: LICENSE
Requires-Dist: pandas
Requires-Dist: numpy
Requires-Dist: psycopg2-binary
Requires-Dist: sqlalchemy
Requires-Dist: google-api-python-client
Requires-Dist: google-auth
Requires-Dist: pymongo
